agents/__init__.py
agents/prebuilt.py
agents/standard_agent.py
agents/goal_preprocessor/__init__.py
agents/goal_preprocessor/base.py
agents/goal_preprocessor/conversational.py
agents/llm/__init__.py
agents/llm/base_llm.py
agents/llm/bedrock.py
agents/llm/exceptions.py
agents/llm/litellm.py
agents/memory/__init__.py
agents/memory/dict_memory.py
agents/prompts/__init__.py
agents/prompts/agent.yaml
agents/prompts/goal_preprocessors/conversational.yaml
agents/prompts/reasoners/react.yaml
agents/prompts/reasoners/rewoo.yaml
agents/reasoner/__init__.py
agents/reasoner/base.py
agents/reasoner/exceptions.py
agents/reasoner/react.py
agents/reasoner/rewoo.py
agents/tools/__init__.py
agents/tools/base.py
agents/tools/exceptions.py
agents/tools/jentic.py
standard_agent-0.1.11.dist-info/licenses/LICENSE
standard_agent-0.1.11.dist-info/licenses/NOTICE
utils/__init__.py
utils/logger.py
utils/observability/__init__.py
utils/observability/observe.py
utils/observability/otel_setup.py
utils/observability/exporters/__init__.py
utils/observability/exporters/langfuse.py
utils/observability/exporters/otel.py
standard_agent-0.1.11.dist-info/METADATA
standard_agent-0.1.11.dist-info/WHEEL
standard_agent-0.1.11.dist-info/top_level.txt
standard_agent-0.1.11.dist-info/RECORD
