Metadata-Version: 2.4
Name: standard-agent
Version: 0.1.11
Summary: A simple, modular library for building AI agents—with a composable core and plug‑in components.
License-Expression: Apache-2.0
Requires-Python: >=3.11
License-File: LICENSE
License-File: NOTICE
Requires-Dist: jentic>=0.9.5
Requires-Dist: openai>=1.100.2
Requires-Dist: pydantic>=2.0
Requires-Dist: python-dotenv>=1.0.0
Requires-Dist: litellm>=1.74.3
Requires-Dist: google-generativeai
Requires-Dist: structlog
Requires-Dist: pyyaml
Provides-Extra: dev
Requires-Dist: pytest>=8.0; extra == "dev"
Requires-Dist: pytest-mock; extra == "dev"
Requires-Dist: ruff; extra == "dev"
Requires-Dist: mypy; extra == "dev"
Provides-Extra: observability
Requires-Dist: opentelemetry-api>=1.36.0; extra == "observability"
Requires-Dist: opentelemetry-sdk>=1.36.0; extra == "observability"
Requires-Dist: opentelemetry-exporter-otlp>=1.36.0; extra == "observability"
Requires-Dist: opentelemetry-instrumentation>=0.57b0; extra == "observability"
Provides-Extra: bedrock
Requires-Dist: boto3>=1.36.0; extra == "bedrock"
Dynamic: license-file
